setup.py
sola_distributions/Binomialdistribution.py
sola_distributions/Gaussiandistribution.py
sola_distributions/Generaldistribution.py
sola_distributions/__init__.py
sola_distributions.egg-info/PKG-INFO
sola_distributions.egg-info/SOURCES.txt
sola_distributions.egg-info/dependency_links.txt
sola_distributions.egg-info/not-zip-safe
sola_distributions.egg-info/top_level.txt